snoopy/__init__.py
snoopy/curl_curl_assembler.py
snoopy/evaluators.py
snoopy/fem_c_mod.cp310-win_amd64.pyd
snoopy/fem_c_mod.cp311-win_amd64.pyd
snoopy/fem_c_mod.cpython-310-x86_64-linux-gnu.so
snoopy/finite_element.py
snoopy/geometry_tools.py
snoopy/grad_grad_assembler.py
snoopy/laplace_subdomain_solver.py
snoopy/materials.py
snoopy/matrix_assembly.py
snoopy/mesh_tools.py
snoopy/mvp_solver.py
snoopy/plot_tools.py
snoopy/racetrack_coil.py
snoopy/red_mvp_solver.py
snoopy/SHiP_functions.py
snoopy_ship-0.1.3.dist-info/METADATA
snoopy_ship-0.1.3.dist-info/WHEEL
snoopy_ship-0.1.3.dist-info/RECORD
