Metadata-Version: 2.3
Name: snoopy-SHiP
Version: 0.1.3
Summary: 
Author: meliebsc
Author-email: melvin.liebsch@cern.ch
Requires-Python: >=3.10,<4.0
Classifier: Programming Language :: Python :: 3
Classifier: Programming Language :: Python :: 3.10
Classifier: Programming Language :: Python :: 3.11
Classifier: Programming Language :: Python :: 3.12
Classifier: Programming Language :: Python :: 3.13
Requires-Dist: gmsh (>=4.13.1,<5.0.0)
Requires-Dist: ipykernel (>=6.29.5,<7.0.0)
Requires-Dist: matplotlib (>=3.10.0,<4.0.0)
Requires-Dist: myst-parser (>=4.0.0,<5.0.0)
Requires-Dist: networkx (>=3.4.2,<4.0.0)
Requires-Dist: numpy (>=2.2.1,<3.0.0)
Requires-Dist: pandas (>=2.2.3,<3.0.0)
Requires-Dist: plotly (>=6.0.0,<7.0.0)
Requires-Dist: pydata-sphinx-theme (>=0.16.1,<0.17.0)
Requires-Dist: pyqt6 (>=6.8.0,<7.0.0)
Requires-Dist: pyvista (>=0.44.2,<0.45.0)
Requires-Dist: scipy (>=1.14.1,<2.0.0)
Requires-Dist: sphinx (>=8.1.3,<9.0.0)
Requires-Dist: sphinx-gallery (>=0.18.0,<0.19.0)
Requires-Dist: sphinxcontrib-apidoc (>=0.5.0,<0.6.0)
Requires-Dist: tqdm (>=4.67.1,<5.0.0)
